{
  "id": "lead_321",
  "mobile_number": "447352327695",
  "email": null,
  "timeline": [
    {
      "id": 5356,
      "lead_id": 321,
      "event_type": "call",
      "timestamp": "2025-08-15T13:54:49.572241",
      "content": "",
      "source": "plivo",
      "event_id": "7690058",
      "raw_data": "{\"type\": \"call\", \"timestamp\": \"2025-08-15T13:54:49.572241\", \"id\": 7690058, \"duration\": \"23\", \"to_number\": \"447352327695\", \"from_number\": \"447460047271\", \"source\": \"plivo\", \"record_url\": \"https://media.plivo.com/v1/Account/MAYZM1ZTM5OTRIZDQ5ZD/Recording/6eb17f55-b687-436f-8ded-cb8abb319a62.wav\"}",
      "created_at": "2025-11-18 10:45:06"
    },
    {
      "id": 5357,
      "lead_id": 321,
      "event_type": "call",
      "timestamp": "2025-08-15T14:10:23.171245",
      "content": "",
      "source": "plivo",
      "event_id": "7690191",
      "raw_data": "{\"type\": \"call\", \"timestamp\": \"2025-08-15T14:10:23.171245\", \"id\": 7690191, \"duration\": \"61\", \"to_number\": \"447352327695\", \"from_number\": \"447460047271\", \"source\": \"plivo\", \"record_url\": \"https://media.plivo.com/v1/Account/MAYZM1ZTM5OTRIZDQ5ZD/Recording/774ee575-9709-43a7-b15a-ccdbb4670fc4.wav\"}",
      "created_at": "2025-11-18 10:45:06"
    },
    {
      "id": 5358,
      "lead_id": 321,
      "event_type": "call",
      "timestamp": "2025-08-19T16:01:00.479092",
      "content": "",
      "source": "plivo",
      "event_id": "7717682",
      "raw_data": "{\"type\": \"call\", \"timestamp\": \"2025-08-19T16:01:00.479092\", \"id\": 7717682, \"duration\": \"24\", \"to_number\": \"447352327695\", \"from_number\": \"447460047271\", \"source\": \"plivo\", \"record_url\": \"https://media.plivo.com/v1/Account/MAYZM1ZTM5OTRIZDQ5ZD/Recording/279e1f68-4135-49e3-9910-94411c82e820.wav\"}",
      "created_at": "2025-11-18 10:45:06"
    },
    {
      "id": 5359,
      "lead_id": 321,
      "event_type": "call",
      "timestamp": "2025-08-19T16:01:42.640958",
      "content": "",
      "source": "plivo",
      "event_id": "7717691",
      "raw_data": "{\"type\": \"call\", \"timestamp\": \"2025-08-19T16:01:42.640958\", \"id\": 7717691, \"duration\": \"14\", \"to_number\": \"447352327695\", \"from_number\": \"447460047271\", \"source\": \"plivo\", \"record_url\": \"https://media.plivo.com/v1/Account/MAYZM1ZTM5OTRIZDQ5ZD/Recording/10b2898a-6425-4f86-99fa-2a4ad5d5b5d5.wav\"}",
      "created_at": "2025-11-18 10:45:06"
    },
    {
      "id": 5360,
      "lead_id": 321,
      "event_type": "email",
      "timestamp": "2025-08-19T16:04:30",
      "content": "",
      "source": "email",
      "event_id": null,
      "raw_data": "{\"type\": \"email\", \"timestamp\": \"2025-08-19T16:04:30\", \"sender_email\": \"rishabh.m@amberstudent.com\", \"recipient_email\": \"kimmychen777@gmail.com\", \"subject\": \"Contact details required\", \"message\": \"Hello Kimmy,\\\\n\\\\nThis is Rishabh from AmberStudent. I see you were looking into IQ The Arcade and have filled out a booking form, but the guarantor's details are missing.\\\\n\\\\nI tried calling you just now but wasn't able to connect. Could you please share your WhatsApp number so I can reach you and help complete your booking?\\\\n\\\\nThanks,\\\\nRishabh\\\\n\\\\n--\\\\n\\\\n[amberstudent.com]\\\\n\\\\nRishabh M\\\\n\\\\nSenior Operation Associate\\\\n\\\\nPhone: [+447460047271]()\\\\n\\\\nWhatsapp: [+447460047271]()\\\\n\\\\nEmail: [rishabh.m@amberstudent.com]()\\\\n\\\\nWebsite: [amberstudent.com]()\", \"snippet\": \"Hello Kimmy, This is Rishabh from AmberStudent. I see you were looking into IQ The Arcade and have filled out a booking form, but the guarantor&#39;s details are missing. I tried calling you just now\", \"direction\": \"outbound\", \"sender_type\": \"agent\", \"agent_email\": \"rishabh.m@amberstudent.com\", \"student_email\": \"kimmychen777@gmail.com\"}",
      "created_at": "2025-11-18 10:45:06"
    },
    {
      "id": 5361,
      "lead_id": 321,
      "event_type": "email",
      "timestamp": "2025-08-19T16:41:05",
      "content": "",
      "source": "email",
      "event_id": null,
      "raw_data": "{\"type\": \"email\", \"timestamp\": \"2025-08-19T16:41:05\", \"sender_email\": \"kimmychen777@gmail.com\", \"recipient_email\": \"rishabh.m@amberstudent.com\", \"subject\": \"Re: Contact details required\", \"message\": \"Hi rishabh,\\\\nMy contact number is 07352 327695. Sorry about the delay.\\\\n\\\\nBest wishes\\\\nKimmy\\\\n\\\\nOn Tue, 19 Aug 2025 at 17:04, Rishabh Mishra <[rishabh.m@amberstudent.com]()> wrote:\\\\n\\\\nHello Kimmy,\\\\n\\\\nThis is Rishabh from AmberStudent. I see you were looking into IQ The Arcade and have filled out a booking form, but the guarantor's details are missing.\\\\n\\\\nI tried calling you just now but wasn't able to connect. Could you please share your WhatsApp number so I can reach you and help complete your booking?\\\\n\\\\nThanks,\\\\nRishabh\\\\n\\\\n--\\\\n\\\\n[amberstudent.com]\\\\n\\\\nRishabh M\\\\n\\\\nSenior Operation Associate\\\\n\\\\nPhone: [+447460047271]()\\\\n\\\\nWhatsapp: [+447460047271]()\\\\n\\\\nEmail: [rishabh.m@amberstudent.com]()\\\\n\\\\nWebsite: [amberstudent.com]()\", \"snippet\": \"Hi rishabh, My contact number is 07352 327695. Sorry about the delay. Best wishes Kimmy On Tue, 19 Aug 2025 at 17:04, Rishabh Mishra &lt;rishabh.m@amberstudent.com&gt; wrote: Hello Kimmy, This is\", \"direction\": \"inbound\", \"sender_type\": \"student\", \"agent_email\": \"rishabh.m@amberstudent.com\", \"student_email\": \"kimmychen777@gmail.com\"}",
      "created_at": "2025-11-18 10:45:06"
    },
    {
      "id": 5362,
      "lead_id": 321,
      "event_type": "email",
      "timestamp": "2025-08-19T17:04:01",
      "content": "",
      "source": "email",
      "event_id": null,
      "raw_data": "{\"type\": \"email\", \"timestamp\": \"2025-08-19T17:04:01\", \"sender_email\": \"rishabh.m@amberstudent.com\", \"recipient_email\": \"kimmychen777@gmail.com\", \"subject\": \"Re: Contact details required\", \"message\": \"Hi Kimmy,\\\\n\\\\nThank you for providing your contact number. I appreciate you getting back to me.\\\\n\\\\nCan you please share your Whatsapp details so that I can connect with you ?\\\\n\\\\nThanks,\\\\nRishabh\\\\n\\\\nOn Tue, Aug 19, 2025 at 10:11\\u202fPM Kimmy Chen <[kimmychen777@gmail.com]()> wrote:\\\\n\\\\nHi rishabh,\\\\nMy contact number is 07352 327695. Sorry about the delay.\\\\n\\\\nBest wishes\\\\nKimmy\\\\n\\\\nOn Tue, 19 Aug 2025 at 17:04, Rishabh Mishra <[rishabh.m@amberstudent.com]()> wrote:\\\\n\\\\nHello Kimmy,\\\\n\\\\nThis is Rishabh from AmberStudent. I see you were looking into IQ The Arcade and have filled out a booking form, but the guarantor's details are missing.\\\\n\\\\nI tried calling you just now but wasn't able to connect. Could you please share your WhatsApp number so I can reach you and help complete your booking?\\\\n\\\\nThanks,\\\\nRishabh\\\\n\\\\n--\\\\n\\\\n[amberstudent.com]\\\\n\\\\nRishabh M\\\\n\\\\nSenior Operation Associate\\\\n\\\\nPhone: [+447460047271]()\\\\n\\\\nWhatsapp: [+447460047271]()\\\\n\\\\nEmail: [rishabh.m@amberstudent.com]()\\\\n\\\\nWebsite: [amberstudent.com]()\\\\n\\\\n--\\\\n\\\\n[amberstudent.com]\\\\n\\\\nRishabh M\\\\n\\\\nSenior Operation Associate\\\\n\\\\nPhone: [+447460047271]()\\\\n\\\\nWhatsapp: [+447460047271]()\\\\n\\\\nEmail: [rishabh.m@amberstudent.com]()\\\\n\\\\nWebsite: [amberstudent.com]()\", \"snippet\": \"Hi Kimmy, Thank you for providing your contact number. I appreciate you getting back to me. Can you please share your Whatsapp details so that I can connect with you ? Thanks, Rishabh On Tue, Aug 19,\", \"direction\": \"outbound\", \"sender_type\": \"agent\", \"agent_email\": \"rishabh.m@amberstudent.com\", \"student_email\": \"kimmychen777@gmail.com\"}",
      "created_at": "2025-11-18 10:45:06"
    },
    {
      "id": 5363,
      "lead_id": 321,
      "event_type": "email",
      "timestamp": "2025-08-19T18:01:24",
      "content": "",
      "source": "email",
      "event_id": null,
      "raw_data": "{\"type\": \"email\", \"timestamp\": \"2025-08-19T18:01:24\", \"sender_email\": \"kimmychen777@gmail.com\", \"recipient_email\": \"rishabh.m@amberstudent.com\", \"subject\": \"Re: Contact details required\", \"message\": \"Hi\\\\nI have already booked and paid for a room the arcade and confirmed with my guarantor\\\\nThank you\\\\n\\\\nBest wishes\\\\nKimmy\\\\n\\\\nOn Tue, 19 Aug 2025 at 18:04, Rishabh Mishra <[rishabh.m@amberstudent.com]()> wrote:\\\\n\\\\nHi Kimmy,\\\\n\\\\nThank you for providing your contact number. I appreciate you getting back to me.\\\\n\\\\nCan you please share your Whatsapp details so that I can connect with you ?\\\\n\\\\nThanks,\\\\nRishabh\\\\n\\\\nOn Tue, Aug 19, 2025 at 10:11\\u202fPM Kimmy Chen <[kimmychen777@gmail.com]()> wrote:\\\\n\\\\nHi rishabh,\\\\nMy contact number is 07352 327695. Sorry about the delay.\\\\n\\\\nBest wishes\\\\nKimmy\\\\n\\\\nOn Tue, 19 Aug 2025 at 17:04, Rishabh Mishra <[rishabh.m@amberstudent.com]()> wrote:\\\\n\\\\nHello Kimmy,\\\\n\\\\nThis is Rishabh from AmberStudent. I see you were looking into IQ The Arcade and have filled out a booking form, but the guarantor's details are missing.\\\\n\\\\nI tried calling you just now but wasn't able to connect. Could you please share your WhatsApp number so I can reach you and help complete your booking?\\\\n\\\\nThanks,\\\\nRishabh\\\\n\\\\n--\\\\n\\\\n[amberstudent.com]\\\\n\\\\nRishabh M\\\\n\\\\nSenior Operation Associate\\\\n\\\\nPhone: [+447460047271]()\\\\n\\\\nWhatsapp: [+447460047271]()\\\\n\\\\nEmail: [rishabh.m@amberstudent.com]()\\\\n\\\\nWebsite: [amberstudent.com]()\\\\n\\\\n--\\\\n\\\\n[amberstudent.com]\\\\n\\\\nRishabh M\\\\n\\\\nSenior Operation Associate\\\\n\\\\nPhone: [+447460047271]()\\\\n\\\\nWhatsapp: [+447460047271]()\\\\n\\\\nEmail: [rishabh.m@amberstudent.com]()\\\\n\\\\nWebsite: [amberstudent.com]()\", \"snippet\": \"Hi I have already booked and paid for a room the arcade and confirmed with my guarantor Thank you Best wishes Kimmy On Tue, 19 Aug 2025 at 18:04, Rishabh Mishra &lt;rishabh.m@amberstudent.com&gt; wrote\", \"direction\": \"inbound\", \"sender_type\": \"student\", \"agent_email\": \"rishabh.m@amberstudent.com\", \"student_email\": \"kimmychen777@gmail.com\"}",
      "created_at": "2025-11-18 10:45:06"
    },
    {
      "id": 5364,
      "lead_id": 321,
      "event_type": "email",
      "timestamp": "2025-08-19T18:02:50",
      "content": "",
      "source": "email",
      "event_id": null,
      "raw_data": "{\"type\": \"email\", \"timestamp\": \"2025-08-19T18:02:50\", \"sender_email\": \"rishabh.m@amberstudent.com\", \"recipient_email\": \"kimmychen777@gmail.com\", \"subject\": \"Re: Contact details required\", \"message\": \"Hi Kimmy,\\\\n\\\\nThank you for the update. Could you please confirm the email ID you used to book the room at IQ The Arcade? This will help us verify the booking details on our end.\\\\n\\\\nThanks,\\\\nRishabh\\\\n\\\\nOn Tue, Aug 19, 2025 at 11:31\\u202fPM Kimmy Chen <[kimmychen777@gmail.com]()> wrote:\\\\n\\\\nHi\\\\nI have already booked and paid for a room the arcade and confirmed with my guarantor\\\\nThank you\\\\n\\\\nBest wishes\\\\nKimmy\\\\n\\\\nOn Tue, 19 Aug 2025 at 18:04, Rishabh Mishra <[rishabh.m@amberstudent.com]()> wrote:\\\\n\\\\nHi Kimmy,\\\\n\\\\nThank you for providing your contact number. I appreciate you getting back to me.\\\\n\\\\nCan you please share your Whatsapp details so that I can connect with you ?\\\\n\\\\nThanks,\\\\nRishabh\\\\n\\\\nOn Tue, Aug 19, 2025 at 10:11\\u202fPM Kimmy Chen <[kimmychen777@gmail.com]()> wrote:\\\\n\\\\nHi rishabh,\\\\nMy contact number is 07352 327695. Sorry about the delay.\\\\n\\\\nBest wishes\\\\nKimmy\\\\n\\\\nOn Tue, 19 Aug 2025 at 17:04, Rishabh Mishra <[rishabh.m@amberstudent.com]()> wrote:\\\\n\\\\nHello Kimmy,\\\\n\\\\nThis is Rishabh from AmberStudent. I see you were looking into IQ The Arcade and have filled out a booking form, but the guarantor's details are missing.\\\\n\\\\nI tried calling you just now but wasn't able to connect. Could you please share your WhatsApp number so I can reach you and help complete your booking?\\\\n\\\\nThanks,\\\\nRishabh\\\\n\\\\n--\\\\n\\\\n[amberstudent.com]\\\\n\\\\nRishabh M\\\\n\\\\nSenior Operation Associate\\\\n\\\\nPhone: [+447460047271]()\\\\n\\\\nWhatsapp: [+447460047271]()\\\\n\\\\nEmail: [rishabh.m@amberstudent.com]()\\\\n\\\\nWebsite: [amberstudent.com]()\\\\n\\\\n--\\\\n\\\\n[amberstudent.com]\\\\n\\\\nRishabh M\\\\n\\\\nSenior Operation Associate\\\\n\\\\nPhone: [+447460047271]()\\\\n\\\\nWhatsapp: [+447460047271]()\\\\n\\\\nEmail: [rishabh.m@amberstudent.com]()\\\\n\\\\nWebsite: [amberstudent.com]()\\\\n\\\\n--\\\\n\\\\n[amberstudent.com]\\\\n\\\\nRishabh M\\\\n\\\\nSenior Operation Associate\\\\n\\\\nPhone: [+447460047271]()\\\\n\\\\nWhatsapp: [+447460047271]()\\\\n\\\\nEmail: [rishabh.m@amberstudent.com]()\\\\n\\\\nWebsite: [amberstudent.com]()\", \"snippet\": \"Hi Kimmy, Thank you for the update. Could you please confirm the email ID you used to book the room at IQ The Arcade? This will help us verify the booking details on our end. Thanks, Rishabh On Tue,\", \"direction\": \"outbound\", \"sender_type\": \"agent\", \"agent_email\": \"rishabh.m@amberstudent.com\", \"student_email\": \"kimmychen777@gmail.com\"}",
      "created_at": "2025-11-18 10:45:06"
    },
    {
      "id": 5365,
      "lead_id": 321,
      "event_type": "call",
      "timestamp": "2025-08-19T18:03:39.448641",
      "content": "",
      "source": "plivo",
      "event_id": "7718597",
      "raw_data": "{\"type\": \"call\", \"timestamp\": \"2025-08-19T18:03:39.448641\", \"id\": 7718597, \"duration\": \"0\", \"to_number\": \"447352327695\", \"from_number\": \"447460047271\", \"source\": \"plivo\"}",
      "created_at": "2025-11-18 10:45:06"
    },
    {
      "id": 5366,
      "lead_id": 321,
      "event_type": "call",
      "timestamp": "2025-08-19T18:04:29.261082",
      "content": "",
      "source": "plivo",
      "event_id": "7718604",
      "raw_data": "{\"type\": \"call\", \"timestamp\": \"2025-08-19T18:04:29.261082\", \"id\": 7718604, \"duration\": \"0\", \"to_number\": \"447352327695\", \"from_number\": \"447460047271\", \"source\": \"plivo\"}",
      "created_at": "2025-11-18 10:45:06"
    },
    {
      "id": 5367,
      "lead_id": 321,
      "event_type": "email",
      "timestamp": "2025-08-19T18:55:48",
      "content": "",
      "source": "email",
      "event_id": null,
      "raw_data": "{\"type\": \"email\", \"timestamp\": \"2025-08-19T18:55:48\", \"sender_email\": \"kimmychen777@gmail.com\", \"recipient_email\": \"rishabh.m@amberstudent.com\", \"subject\": \"Re: Contact details required\", \"message\": \"The email should be the same as this email you're contacting me on\\\\n\\\\nOn Tue, 19 Aug 2025 at 19:03, Rishabh Mishra <[rishabh.m@amberstudent.com]()> wrote:\\\\n\\\\nHi Kimmy,\\\\n\\\\nThank you for the update. Could you please confirm the email ID you used to book the room at IQ The Arcade? This will help us verify the booking details on our end.\\\\n\\\\nThanks,\\\\nRishabh\\\\n\\\\nOn Tue, Aug 19, 2025 at 11:31\\u202fPM Kimmy Chen <[kimmychen777@gmail.com]()> wrote:\\\\n\\\\nHi\\\\nI have already booked and paid for a room the arcade and confirmed with my guarantor\\\\nThank you\\\\n\\\\nBest wishes\\\\nKimmy\\\\n\\\\nOn Tue, 19 Aug 2025 at 18:04, Rishabh Mishra <[rishabh.m@amberstudent.com]()> wrote:\\\\n\\\\nHi Kimmy,\\\\n\\\\nThank you for providing your contact number. I appreciate you getting back to me.\\\\n\\\\nCan you please share your Whatsapp details so that I can connect with you ?\\\\n\\\\nThanks,\\\\nRishabh\\\\n\\\\nOn Tue, Aug 19, 2025 at 10:11\\u202fPM Kimmy Chen <[kimmychen777@gmail.com]()> wrote:\\\\n\\\\nHi rishabh,\\\\nMy contact number is 07352 327695. Sorry about the delay.\\\\n\\\\nBest wishes\\\\nKimmy\\\\n\\\\nOn Tue, 19 Aug 2025 at 17:04, Rishabh Mishra <[rishabh.m@amberstudent.com]()> wrote:\\\\n\\\\nHello Kimmy,\\\\n\\\\nThis is Rishabh from AmberStudent. I see you were looking into IQ The Arcade and have filled out a booking form, but the guarantor's details are missing.\\\\n\\\\nI tried calling you just now but wasn't able to connect. Could you please share your WhatsApp number so I can reach you and help complete your booking?\\\\n\\\\nThanks,\\\\nRishabh\\\\n\\\\n--\\\\n\\\\n[amberstudent.com]\\\\n\\\\nRishabh M\\\\n\\\\nSenior Operation Associate\\\\n\\\\nPhone: [+447460047271]()\\\\n\\\\nWhatsapp: [+447460047271]()\\\\n\\\\nEmail: [rishabh.m@amberstudent.com]()\\\\n\\\\nWebsite: [amberstudent.com]()\\\\n\\\\n--\\\\n\\\\n[amberstudent.com]\\\\n\\\\nRishabh M\\\\n\\\\nSenior Operation Associate\\\\n\\\\nPhone: [+447460047271]()\\\\n\\\\nWhatsapp: [+447460047271]()\\\\n\\\\nEmail: [rishabh.m@amberstudent.com]()\\\\n\\\\nWebsite: [amberstudent.com]()\\\\n\\\\n--\\\\n\\\\n[amberstudent.com]\\\\n\\\\nRishabh M\\\\n\\\\nSenior Operation Associate\\\\n\\\\nPhone: [+447460047271]()\\\\n\\\\nWhatsapp: [+447460047271]()\\\\n\\\\nEmail: [rishabh.m@amberstudent.com]()\\\\n\\\\nWebsite: [amberstudent.com]()\", \"snippet\": \"The email should be the same as this email you&#39;re contacting me on On Tue, 19 Aug 2025 at 19:03, Rishabh Mishra &lt;rishabh.m@amberstudent.com&gt; wrote: Hi Kimmy, Thank you for the update. Could\", \"direction\": \"inbound\", \"sender_type\": \"student\", \"agent_email\": \"rishabh.m@amberstudent.com\", \"student_email\": \"kimmychen777@gmail.com\"}",
      "created_at": "2025-11-18 10:45:06"
    },
    {
      "id": 5368,
      "lead_id": 321,
      "event_type": "call",
      "timestamp": "2025-08-19T18:56:39.341450",
      "content": "",
      "source": "plivo",
      "event_id": "7718968",
      "raw_data": "{\"type\": \"call\", \"timestamp\": \"2025-08-19T18:56:39.341450\", \"id\": 7718968, \"duration\": \"0\", \"to_number\": \"447352327695\", \"from_number\": \"447460047271\", \"source\": \"plivo\"}",
      "created_at": "2025-11-18 10:45:06"
    },
    {
      "id": 5369,
      "lead_id": 321,
      "event_type": "email",
      "timestamp": "2025-08-19T19:04:31",
      "content": "",
      "source": "email",
      "event_id": null,
      "raw_data": "{\"type\": \"email\", \"timestamp\": \"2025-08-19T19:04:31\", \"sender_email\": \"rishabh.m@amberstudent.com\", \"recipient_email\": \"kimmychen777@gmail.com\", \"subject\": \"Re: Contact details required\", \"message\": \"Hi Kimmy,\\\\n\\\\nThank you so much for confirming your email ID.\\\\n\\\\nAs a UCL student who has booked a room at iQ The Arcade, you may be eligible for a cashback offer from us at Amber. It appears that your booking may have been made directly, which means we\\u2019re currently unable to mark it as a referral through our platform.\\\\n\\\\nTo ensure you're able to receive up to \\u00a3100\\u2013\\u00a3150 GBP in cashback from us, we kindly request that you send a quick email to thearcade@iqstudentaccommodation.com stating that you booked your accommodation through Amber. Since you initially filled out the booking form via the UCL accommodation website, simply confirming Amber as your referring agent should be sufficient.\\\\n\\\\nPlease feel free to CC me in that email at rishabh.m@amberstudent.com so I can help track the process and ensure everything goes smoothly.\\\\n\\\\nDo note that this cashback is in addition to the property's \\u00a3750 GBP cashback, which means your total cashback could go up to \\u00a3900 GBP.\\\\n\\\\nLet me know if you have any questions or need help with the message to iQ.\\\\n\\\\nBest regards,\\\\nRishabh\\\\n\\\\nOn Wed, Aug 20, 2025 at 12:26\\u202fAM Kimmy Chen <[kimmychen777@gmail.com]()> wrote:\\\\n\\\\nThe email should be the same as this email you're contacting me on\\\\n\\\\nOn Tue, 19 Aug 2025 at 19:03, Rishabh Mishra <[rishabh.m@amberstudent.com]()> wrote:\\\\n\\\\nHi Kimmy,\\\\n\\\\nThank you for the update. Could you please confirm the email ID you used to book the room at IQ The Arcade? This will help us verify the booking details on our end.\\\\n\\\\nThanks,\\\\nRishabh\\\\n\\\\nOn Tue, Aug 19, 2025 at 11:31\\u202fPM Kimmy Chen <[kimmychen777@gmail.com]()> wrote:\\\\n\\\\nHi\\\\nI have already booked and paid for a room the arcade and confirmed with my guarantor\\\\nThank you\\\\n\\\\nBest wishes\\\\nKimmy\\\\n\\\\nOn Tue, 19 Aug 2025 at 18:04, Rishabh Mishra <[rishabh.m@amberstudent.com]()> wrote:\\\\n\\\\nHi Kimmy,\\\\n\\\\nThank you for providing your contact number. I appreciate you getting back to me.\\\\n\\\\nCan you please share your Whatsapp details so that I can connect with you ?\\\\n\\\\nThanks,\\\\nRishabh\\\\n\\\\nOn Tue, Aug 19, 2025 at 10:11\\u202fPM Kimmy Chen <[kimmychen777@gmail.com]()> wrote:\\\\n\\\\nHi rishabh,\\\\nMy contact number is 07352 327695. Sorry about the delay.\\\\n\\\\nBest wishes\\\\nKimmy\\\\n\\\\nOn Tue, 19 Aug 2025 at 17:04, Rishabh Mishra <[rishabh.m@amberstudent.com]()> wrote:\\\\n\\\\nHello Kimmy,\\\\n\\\\nThis is Rishabh from AmberStudent. I see you were looking into IQ The Arcade and have filled out a booking form, but the guarantor's details are missing.\\\\n\\\\nI tried calling you just now but wasn't able to connect. Could you please share your WhatsApp number so I can reach you and help complete your booking?\\\\n\\\\nThanks,\\\\nRishabh\\\\n\\\\n--\\\\n\\\\n[amberstudent.com]\\\\n\\\\nRishabh M\\\\n\\\\nSenior Operation Associate\\\\n\\\\nPhone: [+447460047271]()\\\\n\\\\nWhatsapp: [+447460047271]()\\\\n\\\\nEmail: [rishabh.m@amberstudent.com]()\\\\n\\\\nWebsite: [amberstudent.com]()\\\\n\\\\n--\\\\n\\\\n[amberstudent.com]\\\\n\\\\nRishabh M\\\\n\\\\nSenior Operation Associate\\\\n\\\\nPhone: [+447460047271]()\\\\n\\\\nWhatsapp: [+447460047271]()\\\\n\\\\nEmail: [rishabh.m@amberstudent.com]()\\\\n\\\\nWebsite: [amberstudent.com]()\\\\n\\\\n--\\\\n\\\\n[amberstudent.com]\\\\n\\\\nRishabh M\\\\n\\\\nSenior Operation Associate\\\\n\\\\nPhone: [+447460047271]()\\\\n\\\\nWhatsapp: [+447460047271]()\\\\n\\\\nEmail: [rishabh.m@amberstudent.com]()\\\\n\\\\nWebsite: [amberstudent.com]()\\\\n\\\\n--\\\\n\\\\n[amberstudent.com]\\\\n\\\\nRishabh M\\\\n\\\\nSenior Operation Associate\\\\n\\\\nPhone: [+447460047271]()\\\\n\\\\nWhatsapp: [+447460047271]()\\\\n\\\\nEmail: [rishabh.m@amberstudent.com]()\\\\n\\\\nWebsite: [amberstudent.com]()\", \"snippet\": \"Hi Kimmy, Thank you so much for confirming your email ID. As a UCL student who has booked a room at iQ The Arcade, you may be eligible for a cashback offer from us at Amber. It appears that your\", \"direction\": \"outbound\", \"sender_type\": \"agent\", \"agent_email\": \"rishabh.m@amberstudent.com\", \"student_email\": \"kimmychen777@gmail.com\"}",
      "created_at": "2025-11-18 10:45:06"
    },
    {
      "id": 5370,
      "lead_id": 321,
      "event_type": "lead_info",
      "timestamp": "2025-09-13T00:00:00",
      "content": "",
      "source": "lead_info",
      "event_id": null,
      "raw_data": "{\"type\": \"lead_info\", \"timestamp\": \"2025-09-13T00:00:00\", \"lead_id\": 3144892, \"user_name\": \"kimmy chen\", \"email\": \"kimmychen777@gmail.com\", \"phone\": \"447352327695\", \"lease_duration\": \"39 week\", \"move_out_date\": \"2026-06-12\", \"budget\": 277, \"budget_currency\": \"pound\", \"budget_duration\": \"weekly\", \"city\": \"London\", \"state\": \"England\", \"country\": \"United Kingdom\", \"region_id\": 14, \"agent_id\": 2666, \"inventory_id\": 1953734}",
      "created_at": "2025-11-18 10:45:06"
    }
  ],
  "transcripts": [
    {
      "id": 210,
      "lead_id": 321,
      "call_id": "7690058",
      "record_url": "https://media.plivo.com/v1/Account/MAYZM1ZTM5OTRIZDQ5ZD/Recording/6eb17f55-b687-436f-8ded-cb8abb319a62.wav",
      "transcript_text": "Speaker A: Hello? Hello?",
      "serial_number": null,
      "transcription_status": "completed",
      "assemblyai_transcript_id": null,
      "processing_time_ms": null,
      "created_at": "2025-11-18 10:45:10"
    },
    {
      "id": 212,
      "lead_id": 321,
      "call_id": "7690191",
      "record_url": "https://media.plivo.com/v1/Account/MAYZM1ZTM5OTRIZDQ5ZD/Recording/774ee575-9709-43a7-b15a-ccdbb4670fc4.wav",
      "transcript_text": "Speaker A: It. Hello? It.",
      "serial_number": null,
      "transcription_status": "completed",
      "assemblyai_transcript_id": null,
      "processing_time_ms": null,
      "created_at": "2025-11-18 10:45:14"
    },
    {
      "id": 215,
      "lead_id": 321,
      "call_id": "7717682",
      "record_url": "https://media.plivo.com/v1/Account/MAYZM1ZTM5OTRIZDQ5ZD/Recording/279e1f68-4135-49e3-9910-94411c82e820.wav",
      "transcript_text": "Speaker A: That's amazing. No, no, no. We're getting like. Yeah, but then trains are really expensive. Like 80 pounds to get to London. Hello. Well, I think I'm gonna get the rail car, So I get 32 off.",
      "serial_number": null,
      "transcription_status": "completed",
      "assemblyai_transcript_id": null,
      "processing_time_ms": null,
      "created_at": "2025-11-18 10:45:18"
    },
    {
      "id": 216,
      "lead_id": 321,
      "call_id": "7717691",
      "record_url": "https://media.plivo.com/v1/Account/MAYZM1ZTM5OTRIZDQ5ZD/Recording/10b2898a-6425-4f86-99fa-2a4ad5d5b5d5.wav",
      "transcript_text": "Speaker A: Hello.",
      "serial_number": null,
      "transcription_status": "completed",
      "assemblyai_transcript_id": null,
      "processing_time_ms": null,
      "created_at": "2025-11-18 10:45:22"
    }
  ],
  "summary": {
    "id": 129,
    "lead_id": 321,
    "requirements_json": "{\"user_persona\": {\"booking_for\": \"self\", \"name\": \"kimmy chen\", \"mobile\": [\"+447352327695\"], \"email\": [\"kimmychen777@gmail.com\"], \"whatsapp\": [], \"student_status\": \"student\", \"nationality\": null}, \"accommodation_requirements\": {\"location\": [\"London\"], \"lease_duration_weeks\": 39, \"room_type\": null, \"budget\": {\"max\": 277, \"currency\": \"GBP\"}, \"bathroom_type\": null, \"kitchen_type\": null, \"dual_occupancy\": null, \"university\": \"UCL\", \"move_in_date\": null, \"dependents\": \"no\", \"amenities\": [], \"housing_type\": null, \"nearby_preferences\": [], \"pet_friendly\": null, \"payment_plan\": null, \"course_year\": null}, \"student_journey\": {\"I20_form\": [], \"university_acceptance\": [\"accepted\", \"UCL\"], \"flight_booking\": [], \"visa_status\": [], \"guarantor\": \"yes_national\"}, \"properties_under_consideration\": {\"properties_considered\": [\"IQ The Arcade\"], \"rooms_considered\": []}, \"other_info\": {\"referral_code_or_offer_discussed\": \"Yes, cashback discussed\"}}",
    "tasks_actionables_json": "{\"tasks\": [{\"type\": \"communication\", \"description\": \"Student Kimmy to send an email to thearcade@iqstudentaccommodation.com confirming that the booking was made through Amber to be eligible for cashback.\", \"due\": \"within_week\", \"status\": \"pending\", \"task_for\": \"student\", \"source_reference\": \"Agent's email on 2025-08-19T19:04:31 requesting student to email the property for cashback eligibility.\"}, {\"type\": \"follow_up\", \"description\": \"Agent Rishabh to track the cashback process after Kimmy sends the confirmation email and assist if needed.\", \"due\": \"within_week\", \"status\": \"pending\", \"task_for\": \"agent\", \"source_reference\": \"Agent's email on 2025-08-19T19:04:31 offering to help track the cashback process.\"}], \"last_agent_response\": \"Agent thanked Kimmy for confirming her email ID and informed her about the cashback offer. Agent requested Kimmy to email the property confirming Amber as the referring agent and to CC the agent to track the cashback process.\", \"suggested_next_step\": \"Student Kimmy should send the confirmation email to thearcade@iqstudentaccommodation.com with Amber as the referring agent and CC the agent to enable cashback processing.\"}",
    "conversation_summary_json": "{\"conversation_summary\": {\"sections\": {\"student_overview\": {\"name\": \"Kimmy Chen\", \"nationality\": \"Not mentioned\", \"student_status\": \"student\", \"contact_info\": \"Phone number 07352 327695, email kimmychen777@gmail.com, WhatsApp requested but not provided\", \"booking_for\": \"self\"}, \"accommodation_preferences\": {\"locations\": \"London\", \"university\": \"UCL\", \"room_type\": \"Not mentioned\", \"budget_range\": \"\\u00a3277 per week\", \"move_in_date\": \"Not mentioned\", \"lease_duration\": \"39 weeks\", \"special_requirements\": \"Not mentioned\"}, \"current_status\": {\"booking_stage\": \"Booking completed and paid\", \"documents_status\": \"Guarantor details confirmed\", \"payment_status\": \"Paid\", \"visa_status\": \"Not mentioned\", \"flight_status\": \"Not mentioned\"}, \"communication_summary\": {\"total_interactions\": \"At least 7 calls and 9 emails\", \"primary_channel\": \"Email\", \"last_contact\": \"2025-09-13 (lead info timestamp), last email on 2025-08-19 19:04\", \"response_time\": \"Student responded within hours to agent emails on 19 Aug 2025\", \"key_moments\": \"Agent requested guarantor details and WhatsApp number; student confirmed booking and payment; agent informed about cashback offer and referral process\"}, \"properties_discussed\": {\"properties_mentioned\": \"IQ The Arcade\", \"viewings_scheduled\": \"Not mentioned\", \"preferences_expressed\": \"Not explicitly mentioned\", \"offers_made\": \"Cashback offer up to \\u00a3100\\u2013\\u00a3150 from Amber plus \\u00a3750 from property, total up to \\u00a3900\"}, \"next_steps\": {\"immediate_actions\": \"Student to email thearcade@iqstudentaccommodation.com confirming Amber as referring agent and CC agent\", \"pending_items\": \"Student WhatsApp details not yet provided\", \"follow_up_required\": \"Agent to assist student with cashback email and track referral confirmation\", \"timeline\": \"Booking lease ends 12 June 2026\"}, \"agent_notes\": {\"student_tone\": \"Polite and cooperative, apologetic for delayed responses\", \"urgency_level\": \"Moderate, booking already completed\", \"complexity\": \"Low complexity, mainly verification and referral process\", \"special_considerations\": \"Student booked directly but eligible for cashback via referral; agent needs to ensure referral is tracked for cashback\"}}}}",
    "combined_summary_json": "{\"requirements\": {\"user_persona\": {\"booking_for\": \"self\", \"name\": \"kimmy chen\", \"mobile\": [\"+447352327695\"], \"email\": [\"kimmychen777@gmail.com\"], \"whatsapp\": [], \"student_status\": \"student\", \"nationality\": null}, \"accommodation_requirements\": {\"location\": [\"London\"], \"lease_duration_weeks\": 39, \"room_type\": null, \"budget\": {\"max\": 277, \"currency\": \"GBP\"}, \"bathroom_type\": null, \"kitchen_type\": null, \"dual_occupancy\": null, \"university\": \"UCL\", \"move_in_date\": null, \"dependents\": \"no\", \"amenities\": [], \"housing_type\": null, \"nearby_preferences\": [], \"pet_friendly\": null, \"payment_plan\": null, \"course_year\": null}, \"student_journey\": {\"I20_form\": [], \"university_acceptance\": [\"accepted\", \"UCL\"], \"flight_booking\": [], \"visa_status\": [], \"guarantor\": \"yes_national\"}, \"properties_under_consideration\": {\"properties_considered\": [\"IQ The Arcade\"], \"rooms_considered\": []}, \"other_info\": {\"referral_code_or_offer_discussed\": \"Yes, cashback discussed\"}}, \"tasks_and_actionables\": {\"tasks\": [{\"type\": \"communication\", \"description\": \"Student Kimmy to send an email to thearcade@iqstudentaccommodation.com confirming that the booking was made through Amber to be eligible for cashback.\", \"due\": \"within_week\", \"status\": \"pending\", \"task_for\": \"student\", \"source_reference\": \"Agent's email on 2025-08-19T19:04:31 requesting student to email the property for cashback eligibility.\"}, {\"type\": \"follow_up\", \"description\": \"Agent Rishabh to track the cashback process after Kimmy sends the confirmation email and assist if needed.\", \"due\": \"within_week\", \"status\": \"pending\", \"task_for\": \"agent\", \"source_reference\": \"Agent's email on 2025-08-19T19:04:31 offering to help track the cashback process.\"}], \"last_agent_response\": \"Agent thanked Kimmy for confirming her email ID and informed her about the cashback offer. Agent requested Kimmy to email the property confirming Amber as the referring agent and to CC the agent to track the cashback process.\", \"suggested_next_step\": \"Student Kimmy should send the confirmation email to thearcade@iqstudentaccommodation.com with Amber as the referring agent and CC the agent to enable cashback processing.\"}, \"conversation_summary\": {\"conversation_summary\": {\"sections\": {\"student_overview\": {\"name\": \"Kimmy Chen\", \"nationality\": \"Not mentioned\", \"student_status\": \"student\", \"contact_info\": \"Phone number 07352 327695, email kimmychen777@gmail.com, WhatsApp requested but not provided\", \"booking_for\": \"self\"}, \"accommodation_preferences\": {\"locations\": \"London\", \"university\": \"UCL\", \"room_type\": \"Not mentioned\", \"budget_range\": \"\\u00a3277 per week\", \"move_in_date\": \"Not mentioned\", \"lease_duration\": \"39 weeks\", \"special_requirements\": \"Not mentioned\"}, \"current_status\": {\"booking_stage\": \"Booking completed and paid\", \"documents_status\": \"Guarantor details confirmed\", \"payment_status\": \"Paid\", \"visa_status\": \"Not mentioned\", \"flight_status\": \"Not mentioned\"}, \"communication_summary\": {\"total_interactions\": \"At least 7 calls and 9 emails\", \"primary_channel\": \"Email\", \"last_contact\": \"2025-09-13 (lead info timestamp), last email on 2025-08-19 19:04\", \"response_time\": \"Student responded within hours to agent emails on 19 Aug 2025\", \"key_moments\": \"Agent requested guarantor details and WhatsApp number; student confirmed booking and payment; agent informed about cashback offer and referral process\"}, \"properties_discussed\": {\"properties_mentioned\": \"IQ The Arcade\", \"viewings_scheduled\": \"Not mentioned\", \"preferences_expressed\": \"Not explicitly mentioned\", \"offers_made\": \"Cashback offer up to \\u00a3100\\u2013\\u00a3150 from Amber plus \\u00a3750 from property, total up to \\u00a3900\"}, \"next_steps\": {\"immediate_actions\": \"Student to email thearcade@iqstudentaccommodation.com confirming Amber as referring agent and CC agent\", \"pending_items\": \"Student WhatsApp details not yet provided\", \"follow_up_required\": \"Agent to assist student with cashback email and track referral confirmation\", \"timeline\": \"Booking lease ends 12 June 2026\"}, \"agent_notes\": {\"student_tone\": \"Polite and cooperative, apologetic for delayed responses\", \"urgency_level\": \"Moderate, booking already completed\", \"complexity\": \"Low complexity, mainly verification and referral process\", \"special_considerations\": \"Student booked directly but eligible for cashback via referral; agent needs to ensure referral is tracked for cashback\"}}}}}",
    "created_at": "2025-11-18 10:45:30",
    "updated_at": "2025-11-18T16:15:30.737126",
    "requirements": {
      "user_persona": {
        "booking_for": "self",
        "name": "kimmy chen",
        "mobile": [
          "+447352327695"
        ],
        "email": [
          "kimmychen777@gmail.com"
        ],
        "whatsapp": [],
        "student_status": "student",
        "nationality": null
      },
      "accommodation_requirements": {
        "location": [
          "London"
        ],
        "lease_duration_weeks": 39,
        "room_type": null,
        "budget": {
          "max": 277,
          "currency": "GBP"
        },
        "bathroom_type": null,
        "kitchen_type": null,
        "dual_occupancy": null,
        "university": "UCL",
        "move_in_date": null,
        "dependents": "no",
        "amenities": [],
        "housing_type": null,
        "nearby_preferences": [],
        "pet_friendly": null,
        "payment_plan": null,
        "course_year": null
      },
      "student_journey": {
        "I20_form": [],
        "university_acceptance": [
          "accepted",
          "UCL"
        ],
        "flight_booking": [],
        "visa_status": [],
        "guarantor": "yes_national"
      },
      "properties_under_consideration": {
        "properties_considered": [
          "IQ The Arcade"
        ],
        "rooms_considered": []
      },
      "other_info": {
        "referral_code_or_offer_discussed": "Yes, cashback discussed"
      }
    },
    "tasks_actionables": {
      "tasks": [
        {
          "type": "communication",
          "description": "Student Kimmy to send an email to thearcade@iqstudentaccommodation.com confirming that the booking was made through Amber to be eligible for cashback.",
          "due": "within_week",
          "status": "pending",
          "task_for": "student",
          "source_reference": "Agent's email on 2025-08-19T19:04:31 requesting student to email the property for cashback eligibility."
        },
        {
          "type": "follow_up",
          "description": "Agent Rishabh to track the cashback process after Kimmy sends the confirmation email and assist if needed.",
          "due": "within_week",
          "status": "pending",
          "task_for": "agent",
          "source_reference": "Agent's email on 2025-08-19T19:04:31 offering to help track the cashback process."
        }
      ],
      "last_agent_response": "Agent thanked Kimmy for confirming her email ID and informed her about the cashback offer. Agent requested Kimmy to email the property confirming Amber as the referring agent and to CC the agent to track the cashback process.",
      "suggested_next_step": "Student Kimmy should send the confirmation email to thearcade@iqstudentaccommodation.com with Amber as the referring agent and CC the agent to enable cashback processing."
    },
    "conversation_summary": {
      "conversation_summary": {
        "sections": {
          "student_overview": {
            "name": "Kimmy Chen",
            "nationality": "Not mentioned",
            "student_status": "student",
            "contact_info": "Phone number 07352 327695, email kimmychen777@gmail.com, WhatsApp requested but not provided",
            "booking_for": "self"
          },
          "accommodation_preferences": {
            "locations": "London",
            "university": "UCL",
            "room_type": "Not mentioned",
            "budget_range": "£277 per week",
            "move_in_date": "Not mentioned",
            "lease_duration": "39 weeks",
            "special_requirements": "Not mentioned"
          },
          "current_status": {
            "booking_stage": "Booking completed and paid",
            "documents_status": "Guarantor details confirmed",
            "payment_status": "Paid",
            "visa_status": "Not mentioned",
            "flight_status": "Not mentioned"
          },
          "communication_summary": {
            "total_interactions": "At least 7 calls and 9 emails",
            "primary_channel": "Email",
            "last_contact": "2025-09-13 (lead info timestamp), last email on 2025-08-19 19:04",
            "response_time": "Student responded within hours to agent emails on 19 Aug 2025",
            "key_moments": "Agent requested guarantor details and WhatsApp number; student confirmed booking and payment; agent informed about cashback offer and referral process"
          },
          "properties_discussed": {
            "properties_mentioned": "IQ The Arcade",
            "viewings_scheduled": "Not mentioned",
            "preferences_expressed": "Not explicitly mentioned",
            "offers_made": "Cashback offer up to £100–£150 from Amber plus £750 from property, total up to £900"
          },
          "next_steps": {
            "immediate_actions": "Student to email thearcade@iqstudentaccommodation.com confirming Amber as referring agent and CC agent",
            "pending_items": "Student WhatsApp details not yet provided",
            "follow_up_required": "Agent to assist student with cashback email and track referral confirmation",
            "timeline": "Booking lease ends 12 June 2026"
          },
          "agent_notes": {
            "student_tone": "Polite and cooperative, apologetic for delayed responses",
            "urgency_level": "Moderate, booking already completed",
            "complexity": "Low complexity, mainly verification and referral process",
            "special_considerations": "Student booked directly but eligible for cashback via referral; agent needs to ensure referral is tracked for cashback"
          }
        }
      }
    },
    "combined_summary": {
      "requirements": {
        "user_persona": {
          "booking_for": "self",
          "name": "kimmy chen",
          "mobile": [
            "+447352327695"
          ],
          "email": [
            "kimmychen777@gmail.com"
          ],
          "whatsapp": [],
          "student_status": "student",
          "nationality": null
        },
        "accommodation_requirements": {
          "location": [
            "London"
          ],
          "lease_duration_weeks": 39,
          "room_type": null,
          "budget": {
            "max": 277,
            "currency": "GBP"
          },
          "bathroom_type": null,
          "kitchen_type": null,
          "dual_occupancy": null,
          "university": "UCL",
          "move_in_date": null,
          "dependents": "no",
          "amenities": [],
          "housing_type": null,
          "nearby_preferences": [],
          "pet_friendly": null,
          "payment_plan": null,
          "course_year": null
        },
        "student_journey": {
          "I20_form": [],
          "university_acceptance": [
            "accepted",
            "UCL"
          ],
          "flight_booking": [],
          "visa_status": [],
          "guarantor": "yes_national"
        },
        "properties_under_consideration": {
          "properties_considered": [
            "IQ The Arcade"
          ],
          "rooms_considered": []
        },
        "other_info": {
          "referral_code_or_offer_discussed": "Yes, cashback discussed"
        }
      },
      "tasks_and_actionables": {
        "tasks": [
          {
            "type": "communication",
            "description": "Student Kimmy to send an email to thearcade@iqstudentaccommodation.com confirming that the booking was made through Amber to be eligible for cashback.",
            "due": "within_week",
            "status": "pending",
            "task_for": "student",
            "source_reference": "Agent's email on 2025-08-19T19:04:31 requesting student to email the property for cashback eligibility."
          },
          {
            "type": "follow_up",
            "description": "Agent Rishabh to track the cashback process after Kimmy sends the confirmation email and assist if needed.",
            "due": "within_week",
            "status": "pending",
            "task_for": "agent",
            "source_reference": "Agent's email on 2025-08-19T19:04:31 offering to help track the cashback process."
          }
        ],
        "last_agent_response": "Agent thanked Kimmy for confirming her email ID and informed her about the cashback offer. Agent requested Kimmy to email the property confirming Amber as the referring agent and to CC the agent to track the cashback process.",
        "suggested_next_step": "Student Kimmy should send the confirmation email to thearcade@iqstudentaccommodation.com with Amber as the referring agent and CC the agent to enable cashback processing."
      },
      "conversation_summary": {
        "conversation_summary": {
          "sections": {
            "student_overview": {
              "name": "Kimmy Chen",
              "nationality": "Not mentioned",
              "student_status": "student",
              "contact_info": "Phone number 07352 327695, email kimmychen777@gmail.com, WhatsApp requested but not provided",
              "booking_for": "self"
            },
            "accommodation_preferences": {
              "locations": "London",
              "university": "UCL",
              "room_type": "Not mentioned",
              "budget_range": "£277 per week",
              "move_in_date": "Not mentioned",
              "lease_duration": "39 weeks",
              "special_requirements": "Not mentioned"
            },
            "current_status": {
              "booking_stage": "Booking completed and paid",
              "documents_status": "Guarantor details confirmed",
              "payment_status": "Paid",
              "visa_status": "Not mentioned",
              "flight_status": "Not mentioned"
            },
            "communication_summary": {
              "total_interactions": "At least 7 calls and 9 emails",
              "primary_channel": "Email",
              "last_contact": "2025-09-13 (lead info timestamp), last email on 2025-08-19 19:04",
              "response_time": "Student responded within hours to agent emails on 19 Aug 2025",
              "key_moments": "Agent requested guarantor details and WhatsApp number; student confirmed booking and payment; agent informed about cashback offer and referral process"
            },
            "properties_discussed": {
              "properties_mentioned": "IQ The Arcade",
              "viewings_scheduled": "Not mentioned",
              "preferences_expressed": "Not explicitly mentioned",
              "offers_made": "Cashback offer up to £100–£150 from Amber plus £750 from property, total up to £900"
            },
            "next_steps": {
              "immediate_actions": "Student to email thearcade@iqstudentaccommodation.com confirming Amber as referring agent and CC agent",
              "pending_items": "Student WhatsApp details not yet provided",
              "follow_up_required": "Agent to assist student with cashback email and track referral confirmation",
              "timeline": "Booking lease ends 12 June 2026"
            },
            "agent_notes": {
              "student_tone": "Polite and cooperative, apologetic for delayed responses",
              "urgency_level": "Moderate, booking already completed",
              "complexity": "Low complexity, mainly verification and referral process",
              "special_considerations": "Student booked directly but eligible for cashback via referral; agent needs to ensure referral is tracked for cashback"
            }
          }
        }
      }
    }
  }
}